cmesdata/__init__.py
cmesdata/future.py
cmesdata/stock.py
cmesdata/third/__init__.py
cmesdata/third/maths.py
cmesdata-1.2.8.dist-info/METADATA
cmesdata-1.2.8.dist-info/WHEEL
cmesdata-1.2.8.dist-info/top_level.txt
cmesdata-1.2.8.dist-info/RECORD
